sigpipes/__init__.py
sigpipes/auxtools.py
sigpipes/emd.py
sigpipes/features.py
sigpipes/joiner.py
sigpipes/megawin.py
sigpipes/pandas.py
sigpipes/pandas_support.py
sigpipes/physionet.py
sigpipes/plotting.py
sigpipes/psigoperator.py
sigpipes/sigcontainer.py
sigpipes/sigfilter.py
sigpipes/sigfuture.py
sigpipes/sigoperator.py
sigpipes/sources.py
sigpipes/__pycache__/__init__.cpython-38.pyc
sigpipes/__pycache__/joiner.cpython-38.pyc
signal_pipes-0.1.16.dist-info/LICENSE
signal_pipes-0.1.16.dist-info/METADATA
signal_pipes-0.1.16.dist-info/WHEEL
signal_pipes-0.1.16.dist-info/top_level.txt
signal_pipes-0.1.16.dist-info/RECORD
