Metadata-Version: 2.1
Name: signal-pipes
Version: 0.1.16
Summary: Stream operation for processing of (physiological) signals
Home-page: UNKNOWN
Author: Department of Informatics, Faculty of Science, University of J.E. Purkyne in Usti nad Labem 
Author-email: Jiri.Fiser@ujep.cz
License: Apache Software License
Platform: UNKNOWN
Classifier: Topic :: Scientific/Engineering :: Bio-Informatics
Classifier: License :: OSI Approved :: Apache Software License
Classifier: Programming Language :: Python :: 3
Classifier: Programming Language :: Python :: 3.6
Requires-Dist: numpy
Requires-Dist: scipy
Requires-Dist: h5py
Requires-Dist: matplotlib
